sketchybar_py/__init__.py
sketchybar_py-0.1.1.dist-info/METADATA
sketchybar_py-0.1.1.dist-info/WHEEL
sketchybar_py-0.1.1.dist-info/licenses/LICENSE
sketchybar_py-0.1.1.dist-info/RECORD
