Metadata-Version: 2.4
Name: sketchybar-py
Version: 0.1.1
Summary: A tiny lib for Sketchybar configuring with Python
Author-email: Dmitry Kuznetsov <dk@lemd.cc>
License-File: LICENSE
Requires-Python: >=3.10
